comp2083/__init__.py
comp2083/basic_motion.py
comp2083/randoms.py
comp2083-0.0.0.dist-info/METADATA
comp2083-0.0.0.dist-info/WHEEL
comp2083-0.0.0.dist-info/top_level.txt
comp2083-0.0.0.dist-info/RECORD
